visdata/__init__.py
visdata/__util.py
visdata/decorators.py
visdata/binned_data/__init__.py
visdata/binned_data/binning.py
visdata/binned_data/profile2d.py
visdata/mathtools/__init__.py
visdata/mathtools/functions.py
visdata/mathtools/intervals.py
visdata/output/__init__.py
visdata/output/general.py
visdata/output/table.py
visdata/plotting/__init__.py
visdata/plotting/compare_results.py
visdata/plotting/geometric_figures.py
visdata/plotting/histogram2d.py
visdata/plotting/marginal_plots.py
visdata/plotting/matplotlib_util.py
visdata-0.2.0.dev1.dist-info/licenses/LICENSE
visdata-0.2.0.dev1.dist-info/METADATA
visdata-0.2.0.dev1.dist-info/WHEEL
visdata-0.2.0.dev1.dist-info/top_level.txt
visdata-0.2.0.dev1.dist-info/RECORD
