Metadata-Version: 2.4
Name: visdata
Version: 0.2.0.dev1
Summary: Package for data visualisation.
Author-email: Philipp Meder <148459685+PhilippMeder@users.noreply.github.com>
License: BSD 3-Clause License
Project-URL: Homepage, https://github.com/philippmeder/visdata
Project-URL: Issues, https://github.com/philippmeder/visdata/issues
Classifier: Intended Audience :: Science/Research
Classifier: License :: OSI Approved :: BSD License
Classifier: Operating System :: OS Independent
Classifier: Programming Language :: Python :: 3
Classifier: Programming Language :: Python :: 3.10
Classifier: Programming Language :: Python :: 3.11
Classifier: Programming Language :: Python :: 3.12
Classifier: Programming Language :: Python :: 3.13
Classifier: Topic :: Scientific/Engineering :: Visualization
Requires-Python: >=3.10
License-File: LICENSE
Requires-Dist: numpy>2
Requires-Dist: matplotlib>3.8
Provides-Extra: dev
Requires-Dist: pytest; extra == "dev"
Requires-Dist: ruff; extra == "dev"
Dynamic: license-file
